<entryFree xmlns="http://www.tei-c.org/ns/1.0" xml:id="uuid-a6880c67-1fa5-32ab-a5fd-89d0d5ed1a98"><revisionDesc status="elaborated"/><editor xml:id="timea.bartha" role="redactor"/><orth>AREOPAG s. n.</orth><gramGrp/><quote xml:lang="ro">Fericită natură, ieromonahul Teodosie! Răsfoitorul „Pidalionului” îşi dă seama că el a fost răsfăţatul mănăstirii, că un spirit dc observaţie just şi caricatural l-a făcut iubit şi i-a dat autoritatea binevoitoare să ilustreze marea majoritate a capitolelor, când cu o figură cât un timbru, vioaie, când cu o compoziţie de areopag.</quote><bibl><ptr target="" type=""/><date/><citedRange>ARGHEZI, PENS. în SCRIERI 29, 259 [1938]</citedRange></bibl><re type=""/><note/></entryFree>