<entryFree xmlns="http://www.tei-c.org/ns/1.0" xml:id="uuid-4dac931c-88f2-3f1c-ae68-8fe0410eb554"><revisionDesc status="elaborated"/><editor xml:id="timea.bartha" role="redactor"/><orth>ANTIDECIZIONISM</orth><gramGrp/><quote xml:lang="ro">Antidecizionismul, nostalgia elegiacă şi aspiraţia ridicată la rangul de principiu îi dau [personalităţii romantice] elasticitatea de a apăra poziţii variate, de a renunţa la necesitatea deciziei şi a-şi îndeplini destinul de eternă aspiraţie.</quote><bibl><ptr target="" type=""/><date/><citedRange>PANDREA, P. C. II, 145 [1946]</citedRange></bibl><re type=""/><note/></entryFree>