<entryFree xmlns="http://www.tei-c.org/ns/1.0" xml:id="uuid-4158fe49-2421-3c6a-a15e-5ee19abd577f"><revisionDesc status="elaborated"/><editor xml:id="emese.g" role="redactor"/><orth>ARHIDUCAT</orth><gramGrp/><quote xml:lang="ro">Colecţia mineralogică ... împreună cu o altă colecţie completă de conhiliile de uscat şi ape dulci din arhiducatul Austrii[i] s-au cumpărat de la Viena de dl marele vornic M. Ghica (a.1836).</quote><bibl><ptr target="" type=""/><date/><citedRange>DICULESCU, V.COTID. 234</citedRange></bibl><re type=""/><note/></entryFree>