<entryFree xmlns="http://www.tei-c.org/ns/1.0" xml:id="uuid-45a9b9fa-3380-391b-9d55-37e8e1107c39"><revisionDesc status="elaborated"/><editor xml:id="emese.g" role="redactor"/><orth>AMATOR, -OARE</orth><gramGrp/><quote xml:lang="ro">Nicu Filipescu, ministrul domeniilor, este un mare amator de covoare orientale; unul din saloanele lui, mobilat în stil oriental, e bogat de o colecţie rară de covoare de Smirna, afgane, belucistane, de dimensiuni impunătoare, şirasuri şi buchare de preţ.</quote><bibl><ptr target="" type=""/><date/><citedRange>C. BACALBAŞA, BUC. IV, 104</citedRange></bibl><re type=""/><note/></entryFree>