<entryFree xmlns="http://www.tei-c.org/ns/1.0" xml:id="uuid-98b4185b-e737-3c53-bfe0-37cdd71bea98"><revisionDesc status="elaborated"/><editor xml:id="emese.g" role="redactor"/><orth>ADULT, -Ă</orth><gramGrp/><quote xml:lang="ro">Omul trebuie să capete prin educaţie o atitudine bună faţă de viaţă, şi asta cât mai devreme (dacă n-ar fi tirania adulţilor).</quote><bibl><ptr target="" type=""/><date/><citedRange>BĂNCILĂ, F. – D., în Opere, VI, 75. [1964]</citedRange></bibl><re type=""/><note/></entryFree>