<entryFree xmlns="http://www.tei-c.org/ns/1.0" xml:id="uuid-52a7799d-e7bd-3d09-a870-8ad0ad26e1da"><revisionDesc status="elaborated"/><editor xml:id="emese.g" role="redactor"/><orth>AGROFITOTEHNIC, -Ă</orth><gramGrp/><quote xml:lang="ro">Cercetările de durată efectuate pe solurile nisipoase … au demonstrat că ameliorarea acestor soluri presupune dirijarea raţională a unui complex de lucrări agropedoameliorative, agrofitotehnice şi hidroameliorative.</quote><bibl><ptr target="" type=""/><date/><citedRange>SOL. ROM. 159[2002]</citedRange></bibl><re type=""/><note/></entryFree>